{
    "train_batch_size": 128,
    "train_micro_batch_size_per_gpu": 64,
    "gradient_accumulation_steps": 1,
    "optimizer": {
        "type": "Adam",
        "params": {
            "lr": 1e-5
        }
    },
    "fp16": {
        "enabled": false
    },
    "bf16": {
        "enabled": true
    },
    "zero_optimization": {
        "stage": 2,
        "offload_optimizer": {
            "device": "cpu"
        },
        "offload_param": {
            "device": "cpu"
        },
        "contiguous_memory_optimization": false,
        "overlap_comm": true,
        "reduce_scatter": true,
        "reduce_bucket_size": 5e8,
        "allgather_bucket_size": 5e8
    },
    "activation_checkpointing": {
        "partition_activations": true,
        "cpu_checkpointing": true,
        "contiguous_memory_optimization": false,
        "synchronize_checkpoint_boundary": true
    },
    "wall_clock_breakdown": false,
    "steps_per_print": 100
}